khatab/__init__.py
khatab/khatab.py
khatab-1.0.dist-info/METADATA
khatab-1.0.dist-info/WHEEL
khatab-1.0.dist-info/top_level.txt
khatab-1.0.dist-info/RECORD
